LICENSE.md
mtls_auth/__init__.py
mtls_auth/apps.py
mtls_auth/middleware.py
mtls_auth/settings.py
mtls_auth/tests.py
mtls_auth/utils.py
django_mtls_auth-0.2.1.dist-info/AUTHORS.md
django_mtls_auth-0.2.1.dist-info/LICENSE.md
django_mtls_auth-0.2.1.dist-info/METADATA
django_mtls_auth-0.2.1.dist-info/WHEEL
django_mtls_auth-0.2.1.dist-info/RECORD
