Metadata-Version: 2.1
Name: django-mtls-auth
Version: 0.2.1
Summary: Enable mMTLS authentication to your Django projects
Home-page: https://github.com/fretscha/django-mtls-auth
License: MIT
Keywords: django,tls,ssl,client-certificate,authentication,nginx,apache2,reverse-proxy
Author: Frederic Tschannen
Author-email: fretscha@umx.net
Requires-Python: >=3.10,<4.0
Classifier: Development Status :: 4 - Beta
Classifier: Environment :: Web Environment
Classifier: Framework :: Django :: 4.2
Classifier: Framework :: Django :: 5.1
Classifier: Intended Audience :: Developers
Classifier: Intended Audience :: Information Technology
Classifier: Intended Audience :: System Administrators
Classifier: License :: OSI Approved :: MIT License
Classifier: Operating System :: OS Independent
Classifier: Programming Language :: Python :: 3
Classifier: Programming Language :: Python :: 3.10
Classifier: Programming Language :: Python :: 3.11
Classifier: Programming Language :: Python :: 3.12
Classifier: Topic :: Internet
Classifier: Topic :: Internet :: WWW/HTTP
Classifier: Topic :: Internet :: WWW/HTTP :: HTTP Servers
Classifier: Topic :: Software Development
Classifier: Topic :: Software Development :: Libraries
Classifier: Topic :: Software Development :: Libraries :: Application Frameworks
Classifier: Topic :: Software Development :: Libraries :: Python Modules
Classifier: Typing :: Typed
Requires-Dist: django (>=4.2,<5.2)
Project-URL: Documentation, https://django-mtls-auth.readthedocs.io
Project-URL: Repository, https://github.com/fretscha/django-mtls-auth
